[
    {
        "id": "1",
        "name": "hexagon",
        "region": {
            "origin": {
                "x": "63",
                "y": "67"
            },
            "size": {
                "width": "208",
                "height": "212"
            }
        }
    },
    {
        "id": "2",
        "name": "hexagon",
        "region": {
            "origin": {
                "x": "15",
                "y": "191"
            },
            "size": {
                "width": "59",
                "height": "235"
            }
        }
    }
]