[
    {
        "id": "1",
        "name": "rectangle",
        "region": {
            "origin": {
                "x": "77",
                "y": "98"
            },
            "size": {
                "width": "217",
                "height": "238"
            }
        }
    },
    {
        "id": "2",
        "name": "triangle",
        "region": {
            "origin": {
                "x": "4",
                "y": "83"
            },
            "size": {
                "width": "34",
                "height": "113"
            }
        }
    }
]