[
    {
        "id": "1",
        "name": "circle",
        "region": {
            "origin": {
                "x": "87",
                "y": "62"
            },
            "size": {
                "width": "222",
                "height": "197"
            }
        }
    },
    {
        "id": "2",
        "name": "circle",
        "region": {
            "origin": {
                "x": "21",
                "y": "210"
            },
            "size": {
                "width": "63",
                "height": "252"
            }
        }
    },
    {
        "id": "3",
        "name": "circle",
        "region": {
            "origin": {
                "x": "4",
                "y": "154"
            },
            "size": {
                "width": "50",
                "height": "200"
            }
        }
    },
    {
        "id": "4",
        "name": "triangle",
        "region": {
            "origin": {
                "x": "172",
                "y": "6"
            },
            "size": {
                "width": "215",
                "height": "49"
            }
        }
    },
    {
        "id": "5",
        "name": "triangle",
        "region": {
            "origin": {
                "x": "19",
                "y": "58"
            },
            "size": {
                "width": "55",
                "height": "94"
            }
        }
    }
]